leicacam/__init__.py
leicacam/async_cam.py
leicacam/cam.py
leicacam/py.typed
leicacam-0.6.0.dist-info/LICENSE
leicacam-0.6.0.dist-info/METADATA
leicacam-0.6.0.dist-info/WHEEL
leicacam-0.6.0.dist-info/top_level.txt
leicacam-0.6.0.dist-info/RECORD
