Metadata-Version: 2.2
Name: leicacam
Version: 0.6.0
Summary: Control Leica microscopes with python
Author-email: Martin Hjelmare <marhje52@gmail.com>
License: MIT
Project-URL: Bug Tracker, https://github.com/MartinHjelmare/leicacam/issues
Project-URL: Changelog, https://github.com/MartinHjelmare/leicacam/blob/main/CHANGELOG.md
Project-URL: documentation, https://leicacam.readthedocs.io
Project-URL: repository, https://github.com/MartinHjelmare/leicacam
Classifier: Development Status :: 4 - Beta
Classifier: Intended Audience :: Developers
Classifier: Natural Language :: English
Classifier: Operating System :: OS Independent
Classifier: Programming Language :: Python :: 3.11
Classifier: Programming Language :: Python :: 3.12
Classifier: Programming Language :: Python :: 3.13
Classifier: Topic :: Software Development :: Libraries
Requires-Python: >=3.11
License-File: LICENSE
Requires-Dist: async_timeout
Requires-Dist: pydebug
